{
    "version": "0.2",
    "language": "en",
    "dictionaries": [
        "en_US",
        "en-gb",
        "typescript",
        "node",
        "html",
        "css",
        "fonts",
        "filetypes",
        "softwareTerms",
        "lorem-ipsum"
    ],
    "words": [
        "Baldim",
        "Fox",
        "Vite",
        "ESLint",
        "Codecov",
        "Stylelint",
        "Axe",
        "dom",
        "tsx",
        "src",
        "onclick",
        "onsubmit",
        "href",
        "tailwindcss",
        "pa11y",
        "lcov",
        "jiti",
        "rollup",
        "zinc",
        "slate",
        "amber",
        "popstate",
        "visualizer",
        "unmount",
        "typecheck",
        "iconify",
        "tsparser",
        "sonarjs"
    ],
    "ignorePaths": [
        "node_modules/**",
        "dist/**",
        ".git/**",
        "coverage/**",
        ".gemini/**",
        "package-lock.json",
        ".cspell.json",
        "docs/**",
        "*.md"
    ],
    "allowCompoundWords": true
}
